pretix_mtn_momo/__init__.py
pretix_mtn_momo/apps.py
pretix_mtn_momo/payment.py
pretix_mtn_momo/signals.py
pretix_mtn_momo/tasks.py
pretix_mtn_momo/urls.py
pretix_mtn_momo/views.py
pretix_mtn_momo/locale/de/LC_MESSAGES/django.mo
pretix_mtn_momo/locale/de/LC_MESSAGES/django.po
pretix_mtn_momo/locale/de_Informal/.gitkeep
pretix_mtn_momo/locale/de_Informal/LC_MESSAGES/django.mo
pretix_mtn_momo/locale/de_Informal/LC_MESSAGES/django.po
pretix_mtn_momo/static/pretix_mtn_momo/.gitkeep
pretix_mtn_momo/static/pretix_mtn_momo/logo.png
pretix_mtn_momo/templates/pretix_mtn_momo/.gitkeep
pretix_mtn_momo/templates/pretix_mtn_momo/checkout_payment_confirm.html
pretix_mtn_momo/templates/pretix_mtn_momo/checkout_payment_form.html
pretix_mtn_momo/templates/pretix_mtn_momo/control.html
pretix_mtn_momo/templates/pretix_mtn_momo/pending.html
pretix_mtn_momo-1.0.0.dist-info/LICENSE
pretix_mtn_momo-1.0.0.dist-info/METADATA
pretix_mtn_momo-1.0.0.dist-info/WHEEL
pretix_mtn_momo-1.0.0.dist-info/entry_points.txt
pretix_mtn_momo-1.0.0.dist-info/top_level.txt
pretix_mtn_momo-1.0.0.dist-info/RECORD
