Metadata-Version: 2.1
Name: pretix-mtn-momo
Version: 1.0.0
Summary: Accept payments through MTN Mobile Money (MoMo), a popular payment method in a number of African countries.
Author-email: pretix team <support@pretix.eu>
Maintainer-email: pretix team <support@pretix.eu>
License: Apache
Project-URL: homepage, https://github.com/pretix/pretix-mtn-momo
Project-URL: repository, https://github.com/pretix/pretix-mtn-momo
Keywords: pretix
License-File: LICENSE
